{
  "patients": [
    {
      "name": "PACIENTEUNO",
      "surname": "",
      "firstSurname": "",
      "secondSurname": "",
      "gender": "",
      "birthDate": "",
      "nif": "asdasd",
      "userType": "Patient",
      "address": {
        "streetName": "",
        "streetNumber": "",
        "doorNumber": "",
        "postalCode": "",
        "city": "asdasd"
      },
      "nhc": "4545",
      "insuranceList": [
        {
          "insuranceCompanyName": "company1",
          "insuranceType": "hola",
          "cardNumber": "34234"
        }
      ],
      "id": 1
    }
  ],
  "professionals": [
    {
      "name": "Abertea",
      "surname": "",
      "firstSurname": "",
      "secondSurname": "",
      "gender": "",
      "birthDate": "",
      "nif": "",
      "userType": "Professional",
      "address": {
        "streetName": "",
        "streetNumber": "",
        "doorNumber": "",
        "postalCode": "",
        "city": ""
      },
      "medicalBoardNumber": "asdasd",
      "professionalType": "Doctor",
      "id": 1
    },
    {
      "name": "hola",
      "surname": "",
      "firstSurname": "",
      "secondSurname": "",
      "gender": "",
      "birthDate": "",
      "nif": "",
      "userType": "Professional",
      "address": {
        "streetName": "asdasdas",
        "streetNumber": "",
        "doorNumber": "",
        "postalCode": "",
        "city": ""
      },
      "medicalBoardNumber": "asdasd",
      "professionalType": "Doctor",
      "id": 2
    }
  ]
}